{
  "attributes": [],
  "classes": [
    {
      "attributes": [],
      "bases": [
        "View"
      ],
      "class_methods": [],
      "decorators": [],
      "docstring": "Point Cloud view.",
      "lineno": 12,
      "methods": [],
      "name": "PointCloud",
      "properties": [],
      "static_methods": []
    }
  ],
  "docstring": "",
  "filepath": "/Users/jrabarisoa/Codes/pixano-workspace/worktree-connect-inference/src/pixano/schemas/views/point_cloud.py",
  "functions": [
    {
      "decorators": [],
      "docstring": "Create a `PointCloud` instance.\n\nArgs:\n    uri: The point cloud URI. Can be empty when using embedded raw_bytes.\n    id: Point cloud ID.\n    record_id: Record ID.\n    logical_name: Logical view name.\n    raw_bytes: Raw point cloud bytes.\n    preview: Thumbnail/preview bytes.\n    preview_format: Preview format (e.g. \"jpeg\", \"png\").\n\nReturns:\n    The created `PointCloud` instance.",
      "is_async": false,
      "lineno": 21,
      "name": "create_point_cloud",
      "parameters": [
        {
          "annotation": "str",
          "default": "''",
          "kind": "ParameterKind.positional_or_keyword",
          "name": "uri"
        },
        {
          "annotation": "str",
          "default": "''",
          "kind": "ParameterKind.positional_or_keyword",
          "name": "id"
        },
        {
          "annotation": "str",
          "default": "''",
          "kind": "ParameterKind.positional_or_keyword",
          "name": "record_id"
        },
        {
          "annotation": "str",
          "default": "''",
          "kind": "ParameterKind.positional_or_keyword",
          "name": "logical_name"
        },
        {
          "annotation": "bytes | None",
          "default": "None",
          "kind": "ParameterKind.positional_or_keyword",
          "name": "raw_bytes"
        },
        {
          "annotation": "bytes",
          "default": "b''",
          "kind": "ParameterKind.positional_or_keyword",
          "name": "preview"
        },
        {
          "annotation": "str",
          "default": "''",
          "kind": "ParameterKind.positional_or_keyword",
          "name": "preview_format"
        }
      ],
      "returns": "PointCloud"
    },
    {
      "decorators": [],
      "docstring": "Check if the given class is a subclass of `PointCloud`.",
      "is_async": false,
      "lineno": 16,
      "name": "is_point_cloud",
      "parameters": [
        {
          "annotation": "bool",
          "default": "False",
          "kind": "ParameterKind.positional_or_keyword",
          "name": "strict"
        }
      ],
      "returns": "bool"
    }
  ],
  "module": "pixano.schemas.views.point_cloud",
  "submodules": []
}
